microsoft/__init__.py
microsoft/store/__init__.py
microsoft/store/partnercenterservices/__init__.py
microsoft/store/partnercenterservices/microsoft_partner_store_apis.py
microsoft/store/partnercenterservices/version.py
microsoft/store/partnercenterservices/models/__init__.py
microsoft/store/partnercenterservices/models/microsoft_marketplace_services_core_service_fault.py
microsoft/store/partnercenterservices/models/microsoft_partner_sdk_contracts_analytics_customer_licenses_deployment_insights.py
microsoft/store/partnercenterservices/models/microsoft_partner_sdk_contracts_analytics_customer_licenses_usage_insights.py
microsoft/store/partnercenterservices/models/microsoft_partner_sdk_contracts_analytics_partner_licenses_deployment_insights.py
microsoft/store/partnercenterservices/models/microsoft_partner_sdk_contracts_analytics_partner_licenses_usage_insights.py
microsoft/store/partnercenterservices/models/microsoft_partner_sdk_contracts_v1_address.py
microsoft/store/partnercenterservices/models/microsoft_partner_sdk_contracts_v1_associated_partner_user.py
microsoft/store/partnercenterservices/models/microsoft_partner_sdk_contracts_v1_authorization_claims.py
microsoft/store/partnercenterservices/models/microsoft_partner_sdk_contracts_v1_billing_profile.py
microsoft/store/partnercenterservices/models/microsoft_partner_sdk_contracts_v1_collections_paged_resource_collection_microsoft_partner_sdk_contracts_v1_customer_user.py
microsoft/store/partnercenterservices/models/microsoft_partner_sdk_contracts_v1_collections_paged_resource_collection_microsoft_partner_sdk_contracts_v1_device_deployment_device.py
microsoft/store/partnercenterservices/models/microsoft_partner_sdk_contracts_v1_collections_paged_resource_collection_microsoft_partner_sdk_contracts_v1_invoice.py
microsoft/store/partnercenterservices/models/microsoft_partner_sdk_contracts_v1_collections_paged_resource_collection_microsoft_partner_sdk_contracts_v1_invoice_line_item.py
partnercenterservices-0.1.2.dist-info/METADATA
partnercenterservices-0.1.2.dist-info/WHEEL
partnercenterservices-0.1.2.dist-info/top_level.txt
partnercenterservices-0.1.2.dist-info/RECORD
