Metadata-Version: 2.1
Name: partnercenterservices
Version: 0.1.2
Summary: Python SDK for Microsoft Partner Center Services API
Home-page: https://github.com/eduardomourar/partner-center-python
Author: Eduardo Rodrigues
Author-email: 
License: MIT
Keywords: api,microsoft,partnercenter
Platform: UNKNOWN
Requires-Dist: msrestazure (>=0.4.7)
